missioncontrol_client/__init__.py
missioncontrol_client-0.0.3.dist-info/METADATA
missioncontrol_client-0.0.3.dist-info/RECORD
missioncontrol_client-0.0.3.dist-info/WHEEL
missioncontrol_client-0.0.3.dist-info/top_level.txt
