Metadata-Version: 2.1
Name: missioncontrol-client
Version: 0.0.3
Summary: python client for the missioncontrol api
Home-page: https://github.com/fleetspace/missioncontrol_client
Author: Fleet Space Technologies
Author-email: UNKNOWN
License: Apache License Version 2.0
Platform: UNKNOWN
Classifier: Programming Language :: Python :: 3
Classifier: Programming Language :: Python :: 3.4
Classifier: Programming Language :: Python :: 3.5
Classifier: Programming Language :: Python :: 3.6
Classifier: Programming Language :: Python :: 3.7
Classifier: Development Status :: 1 - Planning
Classifier: Intended Audience :: Developers
Classifier: Operating System :: OS Independent
Requires-Dist: requests
